LICENSE
MANIFEST.in
README.rst
setup.py
bir_api/__init__.py
bir_api/classes.py
bir_api/conf.py
bir_api/envelopes.py
bir_api/serializers.py
bir_api/views.py
intgr_bir_api.egg-info/PKG-INFO
intgr_bir_api.egg-info/SOURCES.txt
intgr_bir_api.egg-info/dependency_links.txt
intgr_bir_api.egg-info/not-zip-safe
intgr_bir_api.egg-info/requires.txt
intgr_bir_api.egg-info/top_level.txt