Metadata-Version: 1.1
Name: intgr-bir-api
Version: 1.0.5
Summary: An API for BIR1 (Baza Internetowa REGON 1) allows requesting for polish company data providing KRS, REGON or VAT number. It requires private GUS API key.
Home-page: https://github.com/integree/intgr-bir-api
Author: Integree Bussines Solutions
Author-email: dev@integree.eu
License: MIT License
Download-URL: https://pypi.python.org/packages/source/i/intgr-bir-api/intgr-bir-api-1.0.5.zip
Keywords: api bir bir1 gus krs regon nip vat utils integree
Platform: UNKNOWN
Classifier: Development Status :: 4 - Beta
Classifier: Environment :: Web Environment
Classifier: Intended Audience :: Developers
Classifier: License :: OSI Approved :: MIT License
Classifier: Operating System :: OS Independent
Classifier: Programming Language :: Python :: 2
Classifier: Programming Language :: Python :: 2.7
Classifier: Programming Language :: Python :: 3
Classifier: Programming Language :: Python :: 3.3
Classifier: Programming Language :: Python :: 3.4
Classifier: Framework :: Django :: 1.8
Classifier: Framework :: Django :: 1.9
Classifier: Framework :: Django :: 1.10
Classifier: Topic :: Software Development :: Libraries :: Python Modules
